autogqla/__init__.py
autogqla/base.py
autogqla/condition_constructor.py
autogqla/fields/__init__.py
autogqla/fields/base_field.py
autogqla/fields/connections/__init__.py
autogqla/fields/connections/base.py
autogqla/fields/connections/base_loader.py
autogqla/fields/connections/pagination_connection_field.py
autogqla/fields/connections/pagination_details.py
autogqla/fields/connections/pagination_field.py
autogqla/fields/connections/pagination_helpers.py
autogqla/fields/connections/pagination_loader.py
autogqla/fields/connections/relationship_field.py
autogqla/fields/connections/relationship_loader.py
autogqla/fields/identifier_field.py
autogqla/fields/simple_field.py
autogqla/objects/__init__.py
autogqla/objects/helpers.py
autogqla/schema.py
autogqla/spec.py
autogqla/spec_resolver.py
autogqla-0.1.0.dist-info/LICENSE
autogqla-0.1.0.dist-info/WHEEL
autogqla-0.1.0.dist-info/METADATA
autogqla-0.1.0.dist-info/RECORD
